{
    "key": "3WY5D2U3",
    "version": 7885,
    "library": {
        "type": "group",
        "id": 2165756,
        "name": "VICAV",
        "links": {
            "alternate": {
                "href": "https://www.zotero.org/groups/vicav",
                "type": "text/html"
            }
        }
    },
    "links": {
        "self": {
            "href": "https://api.zotero.org/groups/2165756/items/3WY5D2U3",
            "type": "application/json"
        },
        "alternate": {
            "href": "https://www.zotero.org/groups/vicav/items/3WY5D2U3",
            "type": "text/html"
        }
    },
    "meta": {
        "createdByUser": {
            "id": 4622760,
            "username": "StephanPro",
            "name": "",
            "links": {
                "alternate": {
                    "href": "https://www.zotero.org/stephanpro",
                    "type": "text/html"
                }
            }
        },
        "lastModifiedByUser": {
            "id": 2136239,
            "username": "CMoerth",
            "name": "",
            "links": {
                "alternate": {
                    "href": "https://www.zotero.org/cmoerth",
                    "type": "text/html"
                }
            }
        },
        "creatorSummary": "Bar-Moshe",
        "parsedDate": "2018",
        "numChildren": 0
    },
    "data": {
        "key": "3WY5D2U3",
        "version": 7885,
        "itemType": "journalArticle",
        "title": "The historical development of the vowels e and o and their allophones in the Jewish dialect of Baghdad",
        "creators": [
            {
                "creatorType": "author",
                "firstName": "Assaf",
                "lastName": "Bar-Moshe"
            }
        ],
        "abstractNote": "",
        "publicationTitle": "Zeitschrift für Arabische Linguistik",
        "volume": "68",
        "issue": "",
        "pages": "5-30",
        "date": "2018",
        "series": "",
        "seriesTitle": "",
        "seriesText": "",
        "journalAbbreviation": "",
        "language": "",
        "DOI": "",
        "ISSN": "",
        "shortTitle": "",
        "url": "",
        "accessDate": "",
        "archive": "",
        "archiveLocation": "",
        "libraryCatalog": "",
        "callNumber": "",
        "rights": "",
        "extra": "",
        "tags": [
            {
                "tag": "vt:Jewish dialects"
            },
            {
                "tag": "vt:ethnic minorities"
            },
            {
                "tag": "vt:phonology"
            },
            {
                "tag": "vt:sedentary dialect"
            },
            {
                "tag": "vt:urban dialect"
            }
        ],
        "collections": [],
        "relations": {},
        "dateAdded": "2019-01-07T08:54:02Z",
        "dateModified": "2019-01-07T08:57:36Z"
    }
}
