{
    "key": "A227LBUT",
    "version": 5855,
    "library": {
        "type": "group",
        "id": 2165756,
        "name": "VICAV",
        "links": {
            "alternate": {
                "href": "https://www.zotero.org/groups/vicav",
                "type": "text/html"
            }
        }
    },
    "links": {
        "self": {
            "href": "https://api.zotero.org/groups/2165756/items/A227LBUT",
            "type": "application/json"
        },
        "alternate": {
            "href": "https://www.zotero.org/groups/vicav/items/A227LBUT",
            "type": "text/html"
        }
    },
    "meta": {
        "createdByUser": {
            "id": 4438625,
            "username": "Terlan",
            "name": "",
            "links": {
                "alternate": {
                    "href": "https://www.zotero.org/terlan",
                    "type": "text/html"
                }
            }
        },
        "lastModifiedByUser": {
            "id": 2136239,
            "username": "CMoerth",
            "name": "",
            "links": {
                "alternate": {
                    "href": "https://www.zotero.org/cmoerth",
                    "type": "text/html"
                }
            }
        },
        "creatorSummary": "Levin",
        "parsedDate": "1975",
        "numChildren": 0
    },
    "data": {
        "key": "A227LBUT",
        "version": 5855,
        "itemType": "journalArticle",
        "title": "The vernacular poetry of Safiyy al-Din al-?illi, a source for the reconstruction of iraqi Arabic in the 14th century",
        "creators": [
            {
                "creatorType": "author",
                "firstName": "Aryeh",
                "lastName": "Levin"
            }
        ],
        "abstractNote": "",
        "publicationTitle": "Israel Oriental Studies",
        "volume": "5",
        "issue": "",
        "pages": "259-276",
        "date": "1975",
        "series": "",
        "seriesTitle": "",
        "seriesText": "",
        "journalAbbreviation": "",
        "language": "",
        "DOI": "",
        "ISSN": "",
        "shortTitle": "",
        "url": "",
        "accessDate": "",
        "archive": "",
        "archiveLocation": "",
        "libraryCatalog": "",
        "callNumber": "",
        "rights": "",
        "extra": "",
        "tags": [
            {
                "tag": "cnt:Iraq"
            },
            {
                "tag": "vt:general/comparative study"
            },
            {
                "tag": "vt:linguistics/dialectology"
            },
            {
                "tag": "vt:manuscripts"
            },
            {
                "tag": "vt:oral literature"
            },
            {
                "tag": "vt:oral narratives"
            },
            {
                "tag": "vt:oral poetry"
            },
            {
                "tag": "vt:transcribed texts"
            }
        ],
        "collections": [],
        "relations": {},
        "dateAdded": "2018-10-08T15:32:20Z",
        "dateModified": "2018-10-08T16:04:25Z"
    }
}
