{
    "key": "BM2YMCID",
    "version": 7609,
    "library": {
        "type": "group",
        "id": 2165756,
        "name": "VICAV",
        "links": {
            "alternate": {
                "href": "https://www.zotero.org/groups/vicav",
                "type": "text/html"
            }
        }
    },
    "links": {
        "self": {
            "href": "https://api.zotero.org/groups/2165756/items/BM2YMCID",
            "type": "application/json"
        },
        "alternate": {
            "href": "https://www.zotero.org/groups/vicav/items/BM2YMCID",
            "type": "text/html"
        }
    },
    "meta": {
        "createdByUser": {
            "id": 2136239,
            "username": "CMoerth",
            "name": "",
            "links": {
                "alternate": {
                    "href": "https://www.zotero.org/cmoerth",
                    "type": "text/html"
                }
            }
        },
        "creatorSummary": "Sadiqi",
        "parsedDate": "1995",
        "numChildren": 3
    },
    "data": {
        "key": "BM2YMCID",
        "version": 7609,
        "itemType": "journalArticle",
        "title": "The language of women in the city of Fès, Morocco",
        "creators": [
            {
                "creatorType": "author",
                "firstName": "Fatima",
                "lastName": "Sadiqi"
            },
            {
                "creatorType": "editor",
                "firstName": "Moha",
                "lastName": "Ennaji"
            }
        ],
        "abstractNote": "",
        "publicationTitle": "International Journal of the Sociology of Language",
        "volume": "112",
        "issue": "",
        "pages": "63-79",
        "date": "1995",
        "series": "",
        "seriesTitle": "",
        "seriesText": "",
        "journalAbbreviation": "",
        "language": "",
        "DOI": "",
        "ISSN": "",
        "shortTitle": "",
        "url": "",
        "accessDate": "",
        "archive": "",
        "archiveLocation": "",
        "libraryCatalog": "",
        "callNumber": "",
        "rights": "",
        "extra": "(biblid:sadiqi_1995_4514)",
        "tags": [
            {
                "tag": "geo:Fez [34.01, -5.00]"
            },
            {
                "tag": "cnt:Morocco"
            },
            {
                "tag": "vt:Maghreb"
            },
            {
                "tag": "vt:gender aspects"
            },
            {
                "tag": "vt:sedentary dialect"
            },
            {
                "tag": "vt:sociolinguistics"
            },
            {
                "tag": "vt:urban dialect"
            }
        ],
        "collections": [],
        "relations": {},
        "dateAdded": "2018-04-15T16:02:33Z",
        "dateModified": "2018-04-15T16:02:33Z"
    }
}
