{
    "key": "DECLUT9W",
    "version": 2237,
    "library": {
        "type": "group",
        "id": 2165756,
        "name": "VICAV",
        "links": {
            "alternate": {
                "href": "https://www.zotero.org/groups/vicav",
                "type": "text/html"
            }
        }
    },
    "links": {
        "self": {
            "href": "https://api.zotero.org/groups/2165756/items/DECLUT9W",
            "type": "application/json"
        },
        "alternate": {
            "href": "https://www.zotero.org/groups/vicav/items/DECLUT9W",
            "type": "text/html"
        }
    },
    "meta": {
        "createdByUser": {
            "id": 2136239,
            "username": "CMoerth",
            "name": "",
            "links": {
                "alternate": {
                    "href": "https://www.zotero.org/cmoerth",
                    "type": "text/html"
                }
            }
        },
        "creatorSummary": "Herber",
        "parsedDate": "1925",
        "numChildren": 2
    },
    "data": {
        "key": "DECLUT9W",
        "version": 2237,
        "itemType": "journalArticle",
        "title": "Tatouages des prisonniers marocains (arabes, arabisés et berbères)",
        "creators": [
            {
                "creatorType": "author",
                "firstName": "J.",
                "lastName": "Herber"
            }
        ],
        "abstractNote": "",
        "publicationTitle": "Hespéris",
        "volume": "5",
        "issue": "3",
        "pages": "277-309",
        "date": "1925",
        "series": "",
        "seriesTitle": "",
        "seriesText": "",
        "journalAbbreviation": "",
        "language": "",
        "DOI": "",
        "ISSN": "",
        "shortTitle": "",
        "url": "",
        "accessDate": "",
        "archive": "",
        "archiveLocation": "",
        "libraryCatalog": "",
        "callNumber": "",
        "rights": "",
        "extra": "(biblid:herber_1925_3694)",
        "tags": [
            {
                "tag": "cnt:Morocco"
            },
            {
                "tag": "vt:Maghreb"
            },
            {
                "tag": "vt:anthropology"
            },
            {
                "tag": "vt:customs & etiquette"
            },
            {
                "tag": "vt:ethnographic record"
            },
            {
                "tag": "vt:folklore"
            },
            {
                "tag": "vt:general/comparative study"
            },
            {
                "tag": "vt:sociolinguistics"
            }
        ],
        "collections": [],
        "relations": {},
        "dateAdded": "2018-04-15T16:02:33Z",
        "dateModified": "2018-04-15T16:02:33Z"
    }
}
