{
    "key": "HITGZ8JQ",
    "version": 7271,
    "library": {
        "type": "group",
        "id": 2165756,
        "name": "VICAV",
        "links": {
            "alternate": {
                "href": "https://www.zotero.org/groups/vicav",
                "type": "text/html"
            }
        }
    },
    "links": {
        "self": {
            "href": "https://api.zotero.org/groups/2165756/items/HITGZ8JQ",
            "type": "application/json"
        },
        "alternate": {
            "href": "https://www.zotero.org/groups/vicav/items/HITGZ8JQ",
            "type": "text/html"
        }
    },
    "meta": {
        "createdByUser": {
            "id": 2136239,
            "username": "CMoerth",
            "name": "",
            "links": {
                "alternate": {
                    "href": "https://www.zotero.org/cmoerth",
                    "type": "text/html"
                }
            }
        },
        "creatorSummary": "Hadra",
        "parsedDate": "1978",
        "numChildren": 0
    },
    "data": {
        "key": "HITGZ8JQ",
        "version": 7271,
        "itemType": "journalArticle",
        "title": "The relative clause in English and Sudanese spoken Arabic: a contrastive analysis",
        "creators": [
            {
                "creatorType": "author",
                "firstName": "Tawheeda Osman",
                "lastName": "Hadra"
            }
        ],
        "abstractNote": "",
        "publicationTitle": "Sudan Notes and Records",
        "volume": "59",
        "issue": "",
        "pages": "24-46",
        "date": "1978",
        "series": "",
        "seriesTitle": "",
        "seriesText": "",
        "journalAbbreviation": "",
        "language": "",
        "DOI": "",
        "ISSN": "",
        "shortTitle": "",
        "url": "",
        "accessDate": "",
        "archive": "",
        "archiveLocation": "",
        "libraryCatalog": "",
        "callNumber": "",
        "rights": "",
        "extra": "(biblid:hadra_1978_0000)",
        "tags": [
            {
                "tag": "reg:Egypt-Sudan"
            },
            {
                "tag": "cnt:Sudan"
            },
            {
                "tag": "vt:general/comparative study"
            },
            {
                "tag": "vt:syntax"
            }
        ],
        "collections": [],
        "relations": {},
        "dateAdded": "2018-04-15T16:02:33Z",
        "dateModified": "2018-04-15T16:02:33Z"
    }
}
