{
    "key": "J2GGWSPP",
    "version": 2692,
    "library": {
        "type": "group",
        "id": 2165756,
        "name": "VICAV",
        "links": {
            "alternate": {
                "href": "https://www.zotero.org/groups/vicav",
                "type": "text/html"
            }
        }
    },
    "links": {
        "self": {
            "href": "https://api.zotero.org/groups/2165756/items/J2GGWSPP",
            "type": "application/json"
        },
        "alternate": {
            "href": "https://www.zotero.org/groups/vicav/items/J2GGWSPP",
            "type": "text/html"
        }
    },
    "meta": {
        "createdByUser": {
            "id": 2136239,
            "username": "CMoerth",
            "name": "",
            "links": {
                "alternate": {
                    "href": "https://www.zotero.org/cmoerth",
                    "type": "text/html"
                }
            }
        },
        "lastModifiedByUser": {
            "id": 4622760,
            "username": "StephanPro",
            "name": "",
            "links": {
                "alternate": {
                    "href": "https://www.zotero.org/stephanpro",
                    "type": "text/html"
                }
            }
        },
        "creatorSummary": "Alami",
        "parsedDate": "1969",
        "numChildren": 1
    },
    "data": {
        "key": "J2GGWSPP",
        "version": 2692,
        "itemType": "book",
        "title": "Moroccan Arabic intermediate reader, Part II",
        "creators": [
            {
                "creatorType": "author",
                "firstName": "Wali A.",
                "lastName": "Alami"
            }
        ],
        "abstractNote": "",
        "series": "",
        "seriesNumber": "",
        "volume": "",
        "numberOfVolumes": "",
        "edition": "",
        "place": "Bloomington, IN",
        "publisher": "Intensive Language Training Center, Indiana Univeristiy",
        "date": "1969",
        "numPages": "",
        "language": "",
        "ISBN": "",
        "shortTitle": "",
        "url": "",
        "accessDate": "",
        "archive": "",
        "archiveLocation": "",
        "libraryCatalog": "",
        "callNumber": "",
        "rights": "",
        "extra": "(biblid:alami_1969_3307)",
        "tags": [
            {
                "tag": "cnt:Morocco"
            },
            {
                "tag": "vt:conversation/dialogue"
            },
            {
                "tag": "vt:linguistics/dialectology"
            },
            {
                "tag": "vt:teaching materials"
            },
            {
                "tag": "vt:textbook"
            },
            {
                "tag": "vt:transcribed texts"
            }
        ],
        "collections": [],
        "relations": {},
        "dateAdded": "2018-04-15T16:02:33Z",
        "dateModified": "2018-05-05T15:13:35Z"
    }
}
