{
    "key": "MNMBKX8P",
    "version": 5962,
    "library": {
        "type": "group",
        "id": 2165756,
        "name": "VICAV",
        "links": {
            "alternate": {
                "href": "https://www.zotero.org/groups/vicav",
                "type": "text/html"
            }
        }
    },
    "links": {
        "self": {
            "href": "https://api.zotero.org/groups/2165756/items/MNMBKX8P",
            "type": "application/json"
        },
        "alternate": {
            "href": "https://www.zotero.org/groups/vicav/items/MNMBKX8P",
            "type": "text/html"
        }
    },
    "meta": {
        "createdByUser": {
            "id": 4438625,
            "username": "Terlan",
            "name": "",
            "links": {
                "alternate": {
                    "href": "https://www.zotero.org/terlan",
                    "type": "text/html"
                }
            }
        },
        "lastModifiedByUser": {
            "id": 2136239,
            "username": "CMoerth",
            "name": "",
            "links": {
                "alternate": {
                    "href": "https://www.zotero.org/cmoerth",
                    "type": "text/html"
                }
            }
        },
        "creatorSummary": "Cohen and Vanhove",
        "parsedDate": "1984",
        "numChildren": 0
    },
    "data": {
        "key": "MNMBKX8P",
        "version": 5962,
        "itemType": "journalArticle",
        "title": "La cantilène maltaise du XVè siècle: Remarques linguistiques",
        "creators": [
            {
                "creatorType": "author",
                "firstName": "David",
                "lastName": "Cohen"
            },
            {
                "creatorType": "author",
                "firstName": "Martine",
                "lastName": "Vanhove"
            }
        ],
        "abstractNote": "",
        "publicationTitle": "Groupe Linguistique d'Études Chamito-Sémitiques",
        "volume": "29-30",
        "issue": "",
        "pages": "177-200",
        "date": "1984-1986",
        "series": "",
        "seriesTitle": "",
        "seriesText": "",
        "journalAbbreviation": "",
        "language": "",
        "DOI": "",
        "ISSN": "",
        "shortTitle": "",
        "url": "",
        "accessDate": "",
        "archive": "",
        "archiveLocation": "",
        "libraryCatalog": "",
        "callNumber": "",
        "rights": "",
        "extra": "",
        "tags": [
            {
                "tag": "cnt:Malta"
            },
            {
                "tag": "vt:Maghreb"
            },
            {
                "tag": "vt:ethnographic record"
            },
            {
                "tag": "vt:folklore"
            },
            {
                "tag": "vt:general/comparative study"
            },
            {
                "tag": "vt:music"
            },
            {
                "tag": "vt:oral literature"
            },
            {
                "tag": "vt:oral narratives"
            },
            {
                "tag": "vt:songs"
            },
            {
                "tag": "vt:transcribed texts"
            }
        ],
        "collections": [],
        "relations": {},
        "dateAdded": "2018-10-01T09:34:32Z",
        "dateModified": "2018-10-01T09:36:07Z"
    }
}
