{
    "key": "NUV5E9A4",
    "version": 2320,
    "library": {
        "type": "group",
        "id": 2165756,
        "name": "VICAV",
        "links": {
            "alternate": {
                "href": "https://www.zotero.org/groups/vicav",
                "type": "text/html"
            }
        }
    },
    "links": {
        "self": {
            "href": "https://api.zotero.org/groups/2165756/items/NUV5E9A4",
            "type": "application/json"
        },
        "alternate": {
            "href": "https://www.zotero.org/groups/vicav/items/NUV5E9A4",
            "type": "text/html"
        }
    },
    "meta": {
        "createdByUser": {
            "id": 2136239,
            "username": "CMoerth",
            "name": "",
            "links": {
                "alternate": {
                    "href": "https://www.zotero.org/cmoerth",
                    "type": "text/html"
                }
            }
        },
        "creatorSummary": "Zoubid",
        "parsedDate": "2011",
        "numChildren": 0
    },
    "data": {
        "key": "NUV5E9A4",
        "version": 2320,
        "itemType": "book",
        "title": "Die Mundart der Hyâyna in Marokko",
        "creators": [
            {
                "creatorType": "author",
                "firstName": "Rachida",
                "lastName": "Zoubid"
            }
        ],
        "abstractNote": "",
        "series": "",
        "seriesNumber": "",
        "volume": "",
        "numberOfVolumes": "",
        "edition": "",
        "place": "Göttingen",
        "publisher": "Optimus Verlag",
        "date": "2011",
        "numPages": "511",
        "language": "",
        "ISBN": "",
        "shortTitle": "",
        "url": "",
        "accessDate": "",
        "archive": "",
        "archiveLocation": "",
        "libraryCatalog": "",
        "callNumber": "",
        "rights": "",
        "extra": "(biblid:zoubid_2011_0000)",
        "tags": [
            {
                "tag": "reg:Maghreb []"
            },
            {
                "tag": "cnt:Morocco"
            },
            {
                "tag": "vt:bedouin dialect"
            },
            {
                "tag": "vt:description of dialect"
            },
            {
                "tag": "vt:lexicon"
            },
            {
                "tag": "vt:morphology"
            },
            {
                "tag": "vt:phonology"
            },
            {
                "tag": "vt:transcribed texts"
            }
        ],
        "collections": [],
        "relations": {},
        "dateAdded": "2018-04-15T16:02:33Z",
        "dateModified": "2018-04-15T16:02:33Z"
    }
}
