{
    "key": "TNDAUPBW",
    "version": 8008,
    "library": {
        "type": "group",
        "id": 2165756,
        "name": "VICAV",
        "links": {
            "alternate": {
                "href": "https://www.zotero.org/groups/vicav",
                "type": "text/html"
            }
        }
    },
    "links": {
        "self": {
            "href": "https://api.zotero.org/groups/2165756/items/TNDAUPBW",
            "type": "application/json"
        },
        "alternate": {
            "href": "https://www.zotero.org/groups/vicav/items/TNDAUPBW",
            "type": "text/html"
        }
    },
    "meta": {
        "createdByUser": {
            "id": 2136239,
            "username": "CMoerth",
            "name": "",
            "links": {
                "alternate": {
                    "href": "https://www.zotero.org/cmoerth",
                    "type": "text/html"
                }
            }
        },
        "creatorSummary": "Colin and Laoust",
        "parsedDate": "1932",
        "numChildren": 0
    },
    "data": {
        "key": "TNDAUPBW",
        "version": 8008,
        "itemType": "book",
        "title": "Le milieu indigène au Maroc: les parlers",
        "creators": [
            {
                "creatorType": "author",
                "firstName": "Georges Séraphin",
                "lastName": "Colin"
            },
            {
                "creatorType": "author",
                "firstName": "Emile",
                "lastName": "Laoust"
            }
        ],
        "abstractNote": "",
        "series": "",
        "seriesNumber": "",
        "volume": "",
        "numberOfVolumes": "",
        "edition": "",
        "place": "Rabat",
        "publisher": "Ecole du Livre",
        "date": "1932",
        "numPages": "",
        "language": "",
        "ISBN": "",
        "shortTitle": "",
        "url": "",
        "accessDate": "",
        "archive": "",
        "archiveLocation": "",
        "libraryCatalog": "",
        "callNumber": "",
        "rights": "",
        "extra": "(biblid:colin_1932_3566)",
        "tags": [
            {
                "tag": "cnt:Morocco"
            },
            {
                "tag": "vt:Maghreb"
            },
            {
                "tag": "vt:berber languages"
            },
            {
                "tag": "vt:contact linguistics"
            },
            {
                "tag": "vt:diachronic perspective"
            },
            {
                "tag": "vt:sociolinguistics"
            }
        ],
        "collections": [],
        "relations": {},
        "dateAdded": "2018-04-15T16:02:33Z",
        "dateModified": "2018-09-03T18:30:01Z"
    }
}
