{
    "key": "UKBNFHNS",
    "version": 8792,
    "library": {
        "type": "group",
        "id": 2165756,
        "name": "VICAV",
        "links": {
            "alternate": {
                "href": "https://www.zotero.org/groups/vicav",
                "type": "text/html"
            }
        }
    },
    "links": {
        "self": {
            "href": "https://api.zotero.org/groups/2165756/items/UKBNFHNS",
            "type": "application/json"
        },
        "alternate": {
            "href": "https://www.zotero.org/groups/vicav/items/UKBNFHNS",
            "type": "text/html"
        }
    },
    "meta": {
        "createdByUser": {
            "id": 4622760,
            "username": "StephanPro",
            "name": "",
            "links": {
                "alternate": {
                    "href": "https://www.zotero.org/stephanpro",
                    "type": "text/html"
                }
            }
        },
        "lastModifiedByUser": {
            "id": 2136239,
            "username": "CMoerth",
            "name": "",
            "links": {
                "alternate": {
                    "href": "https://www.zotero.org/cmoerth",
                    "type": "text/html"
                }
            }
        },
        "creatorSummary": "Caubet",
        "parsedDate": "2018",
        "numChildren": 0
    },
    "data": {
        "key": "UKBNFHNS",
        "version": 8792,
        "itemType": "bookSection",
        "title": "Darija and the construction of \"Moroccanness\"",
        "creators": [
            {
                "creatorType": "author",
                "firstName": "Dominique",
                "lastName": "Caubet"
            },
            {
                "creatorType": "editor",
                "firstName": "Reem",
                "lastName": "Bassiouney"
            }
        ],
        "abstractNote": "",
        "bookTitle": "Identity and dialect performance: A study of communities and dialects",
        "series": "",
        "seriesNumber": "",
        "volume": "",
        "numberOfVolumes": "",
        "edition": "",
        "place": "London & New York",
        "publisher": "Routledge",
        "date": "2018",
        "pages": "99-124",
        "language": "",
        "ISBN": "",
        "shortTitle": "",
        "url": "",
        "accessDate": "",
        "archive": "",
        "archiveLocation": "",
        "libraryCatalog": "",
        "callNumber": "",
        "rights": "",
        "extra": "",
        "tags": [
            {
                "tag": "cnt:Morocco"
            },
            {
                "tag": "vt:Maghreb"
            },
            {
                "tag": "vt:diglossia"
            },
            {
                "tag": "vt:ethnography"
            },
            {
                "tag": "vt:sociolinguistics"
            }
        ],
        "collections": [],
        "relations": {},
        "dateAdded": "2019-03-14T10:32:41Z",
        "dateModified": "2019-03-14T10:33:42Z"
    }
}
