{
    "key": "UR97NCQ2",
    "version": 8264,
    "library": {
        "type": "group",
        "id": 2165756,
        "name": "VICAV",
        "links": {
            "alternate": {
                "href": "https://www.zotero.org/groups/vicav",
                "type": "text/html"
            }
        }
    },
    "links": {
        "self": {
            "href": "https://api.zotero.org/groups/2165756/items/UR97NCQ2",
            "type": "application/json"
        },
        "alternate": {
            "href": "https://www.zotero.org/groups/vicav/items/UR97NCQ2",
            "type": "text/html"
        }
    },
    "meta": {
        "createdByUser": {
            "id": 2136239,
            "username": "CMoerth",
            "name": "",
            "links": {
                "alternate": {
                    "href": "https://www.zotero.org/cmoerth",
                    "type": "text/html"
                }
            }
        },
        "creatorSummary": "Nissabouri",
        "parsedDate": "1999",
        "numChildren": 0
    },
    "data": {
        "key": "UR97NCQ2",
        "version": 8264,
        "itemType": "bookSection",
        "title": "État des lieux et dynamiques multilingues en Arabe Marocain",
        "creators": [
            {
                "creatorType": "author",
                "firstName": "Abdelfattah",
                "lastName": "Nissabouri"
            },
            {
                "creatorType": "editor",
                "firstName": "Francis",
                "lastName": "Manzano"
            }
        ],
        "abstractNote": "",
        "bookTitle": "Langues du Maghreb et du Sud méditerranéen",
        "series": "",
        "seriesNumber": "",
        "volume": "",
        "numberOfVolumes": "",
        "edition": "",
        "place": "Rennes",
        "publisher": "P.U. Rennes",
        "date": "1999",
        "pages": "109-127",
        "language": "",
        "ISBN": "",
        "shortTitle": "",
        "url": "",
        "accessDate": "",
        "archive": "",
        "archiveLocation": "",
        "libraryCatalog": "",
        "callNumber": "",
        "rights": "",
        "extra": "(biblid:nissabouri_1999_3895)",
        "tags": [
            {
                "tag": "cnt:Morocco"
            },
            {
                "tag": "vt:Maghreb"
            },
            {
                "tag": "vt:berber languages"
            },
            {
                "tag": "vt:contact linguistics"
            },
            {
                "tag": "vt:french language"
            }
        ],
        "collections": [],
        "relations": {},
        "dateAdded": "2018-04-15T16:02:33Z",
        "dateModified": "2018-04-15T16:02:33Z"
    }
}
