{
    "key": "V8EVXJ75",
    "version": 5621,
    "library": {
        "type": "group",
        "id": 2165756,
        "name": "VICAV",
        "links": {
            "alternate": {
                "href": "https://www.zotero.org/groups/vicav",
                "type": "text/html"
            }
        }
    },
    "links": {
        "self": {
            "href": "https://api.zotero.org/groups/2165756/items/V8EVXJ75",
            "type": "application/json"
        },
        "alternate": {
            "href": "https://www.zotero.org/groups/vicav/items/V8EVXJ75",
            "type": "text/html"
        }
    },
    "meta": {
        "createdByUser": {
            "id": 4622760,
            "username": "StephanPro",
            "name": "",
            "links": {
                "alternate": {
                    "href": "https://www.zotero.org/stephanpro",
                    "type": "text/html"
                }
            }
        },
        "lastModifiedByUser": {
            "id": 2136239,
            "username": "CMoerth",
            "name": "",
            "links": {
                "alternate": {
                    "href": "https://www.zotero.org/cmoerth",
                    "type": "text/html"
                }
            }
        },
        "creatorSummary": "Avram",
        "parsedDate": "2017",
        "numChildren": 0
    },
    "data": {
        "key": "V8EVXJ75",
        "version": 5621,
        "itemType": "bookSection",
        "title": "Sources of Gulf Pidgin Arabic Features",
        "creators": [
            {
                "creatorType": "author",
                "firstName": "Andrei A.",
                "lastName": "Avram"
            },
            {
                "creatorType": "editor",
                "firstName": "Simone",
                "lastName": "Bettega"
            },
            {
                "creatorType": "editor",
                "firstName": "Fabio",
                "lastName": "Gasparini"
            }
        ],
        "abstractNote": "",
        "bookTitle": "Linguistic Studies in the Arabian Gulf",
        "series": "",
        "seriesNumber": "",
        "volume": "",
        "numberOfVolumes": "",
        "edition": "",
        "place": "Torino",
        "publisher": "Università di Torino",
        "date": "2017",
        "pages": "131-151",
        "language": "",
        "ISBN": "",
        "shortTitle": "",
        "url": "",
        "accessDate": "",
        "archive": "",
        "archiveLocation": "",
        "libraryCatalog": "",
        "callNumber": "",
        "rights": "",
        "extra": "",
        "tags": [
            {
                "tag": "reg:Arabian Peninsula [22.36, 46.81]"
            },
            {
                "tag": "reg:Gulf [26.57, 49.55]"
            },
            {
                "tag": "vt:contact linguistics"
            },
            {
                "tag": "vt:conversation/dialogue"
            },
            {
                "tag": "vt:general/comparative study"
            },
            {
                "tag": "vt:linguistics/dialectology"
            },
            {
                "tag": "vt:transcribed texts"
            }
        ],
        "collections": [],
        "relations": {},
        "dateAdded": "2018-10-29T11:48:35Z",
        "dateModified": "2018-10-29T11:50:49Z"
    }
}
